gammu/__init__.py
gammu/_gammu.cp38-win32.pyd
gammu/asyncworker.py
gammu/data.py
gammu/exception.py
gammu/smsd.py
gammu/worker.py
python_gammu-3.2.3.dist-info/AUTHORS
python_gammu-3.2.3.dist-info/COPYING
python_gammu-3.2.3.dist-info/METADATA
python_gammu-3.2.3.dist-info/WHEEL
python_gammu-3.2.3.dist-info/top_level.txt
python_gammu-3.2.3.dist-info/RECORD
