Metadata-Version: 2.1
Name: python-gammu
Version: 3.2.3
Summary: Gammu bindings
Home-page: https://wammu.eu/python-gammu/
Author: Michal Cihar
Author-email: michal@cihar.com
License: GPLv2+
Download-URL: https://wammu.eu/download/python-gammu/
Keywords: mobile,phone,SMS,contact,gammu,calendar,todo
Platform: Linux
Platform: Mac OSX
Platform: Windows XP/2000/NT
Platform: Windows 95/98/ME
Classifier: Development Status :: 6 - Mature
Classifier: Intended Audience :: Developers
Classifier: Intended Audience :: Telecommunications Industry
Classifier: License :: OSI Approved :: GNU General Public License v2 or later (GPLv2+)
Classifier: Operating System :: MacOS
Classifier: Operating System :: Microsoft :: Windows
Classifier: Operating System :: POSIX
Classifier: Operating System :: Unix
Classifier: Programming Language :: C
Classifier: Programming Language :: Python
Classifier: Programming Language :: Python :: 3
Classifier: Programming Language :: Python :: 3.6
Classifier: Programming Language :: Python :: 3.7
Classifier: Programming Language :: Python :: 3.8
Classifier: Programming Language :: Python :: 3.9
Classifier: Topic :: Communications :: Telephony
Classifier: Topic :: Software Development :: Libraries :: Python Modules
Classifier: Topic :: System :: Hardware
Requires-Python: >=3.6
License-File: COPYING
License-File: AUTHORS
